pkb_client/__init__.py
pkb_client/cli/__init__.py
pkb_client/cli/cli.py
pkb_client/client/__init__.py
pkb_client/client/bind_file.py
pkb_client/client/client.py
pkb_client/client/dns.py
pkb_client/client/dnssec.py
pkb_client/client/domain.py
pkb_client/client/forwarding.py
pkb_client/client/ssl_cert.py
tests/__init__.py
tests/bind_file.py
tests/client.py
tests/data/__init__.py
pkb_client-2.2.0.dist-info/METADATA
pkb_client-2.2.0.dist-info/WHEEL
pkb_client-2.2.0.dist-info/entry_points.txt
pkb_client-2.2.0.dist-info/top_level.txt
pkb_client-2.2.0.dist-info/RECORD
