Metadata-Version: 2.4
Name: pkb_client
Version: 2.2.0
Summary: Python client for the Porkbun API
Home-page: https://github.com/infinityofspace/pkb_client
Author: infinityofspace
License: MIT
Classifier: Programming Language :: Python :: 3
Classifier: Programming Language :: Python :: 3.9
Classifier: Programming Language :: Python :: 3.10
Classifier: Programming Language :: Python :: 3.11
Classifier: Programming Language :: Python :: 3.12
Classifier: Programming Language :: Python :: 3.13
Classifier: License :: OSI Approved :: MIT License
Classifier: Topic :: Internet :: WWW/HTTP
Classifier: Topic :: Internet :: Name Service (DNS)
Classifier: Topic :: Utilities
Classifier: Topic :: System :: Systems Administration
Requires-Python: >=3.9
Requires-Dist: setuptools>=39.0.1
Requires-Dist: requests>=2.20.0
Requires-Dist: dnspython~=2.7
Dynamic: author
Dynamic: classifier
Dynamic: description
Dynamic: description-content-type
Dynamic: home-page
Dynamic: license
Dynamic: requires-dist
Dynamic: requires-python
Dynamic: summary
